ssi/__init__.py
ssi/align.py
ssi/cmap.py
ssi/img.py
ssi/lorri.py
ssi/photometry.py
ssi/pixel.py
ssi/ssi.py
ssi/geol/__init__.py
ssi/geol/cmap.py
ssi/geol/data.py
ssi/geol/europa.py
ssi/geol/pluto.py
ssi/geol/units.py
ssi/geol/data/Europa_geol_map.png
ssi/geol/data/Pluto_geol_map.png
ssi/geometry/__init__.py
ssi/geometry/contour.py
ssi/geometry/quaternions.py
ssi/geometry/vectors.py
ssi/isis/__init__.py
ssi/isis/dtime.py
ssi/isis/errors.py
ssi/isis/isis.py
ssi/isis/labels.py
ssi/isis/original_labels.py
ssi/isis/tables.py
ssi/isis/vars.py
ssi/misc/__init__.py
ssi/misc/geojson.py
galileo_ssi-1.9.4.dist-info/LICENSE.md
galileo_ssi-1.9.4.dist-info/METADATA
galileo_ssi-1.9.4.dist-info/WHEEL
galileo_ssi-1.9.4.dist-info/top_level.txt
galileo_ssi-1.9.4.dist-info/RECORD
