Metadata-Version: 2.1
Name: galileo-ssi
Version: 1.9.4
Summary: Python parser for Galileo SSI instrument
Home-page: https://github.com/seignovert/galileo-ssi
Author: Benoit Seignovert
Author-email: benoit.a.seignovert@jpl.nasa.gov
License: MIT
Platform: UNKNOWN
Requires-Python: >=3.6
Requires-Dist: numpy
Requires-Dist: matplotlib
Requires-Dist: pvl
